curler.py
curler-0.2.2.dist-info/LICENSE
curler-0.2.2.dist-info/METADATA
curler-0.2.2.dist-info/WHEEL
curler-0.2.2.dist-info/top_level.txt
curler-0.2.2.dist-info/RECORD
