Metadata-Version: 2.1
Name: curler
Version: 0.2.2
Summary: Import curl command in python and use it with requests, httpx, etc. libraries.
Home-page: https://github.com/arv-anshul/curler/
Author: arv-anshul
Author-email: arv.anshul.1864@gmail.com
License: MIT
Classifier: License :: OSI Approved :: MIT License
Classifier: Programming Language :: Python :: 3.9
Classifier: Programming Language :: Python :: 3.10
Classifier: Programming Language :: Python :: 3.11
Classifier: Programming Language :: Python :: 3.12
Classifier: Operating System :: OS Independent
Requires-Python: >=3.9
License-File: LICENSE
Provides-Extra: dev
Requires-Dist: twine >=4.0.2 ; extra == 'dev'
